__init__.py
homeTools.py
HomePy/__init__.py
HomePy-0.0.2.dist-info/LICENSE
HomePy-0.0.2.dist-info/METADATA
HomePy-0.0.2.dist-info/WHEEL
HomePy-0.0.2.dist-info/top_level.txt
HomePy-0.0.2.dist-info/RECORD
